sap_datasphere_mcp/__init__.py
sap_datasphere_mcp/__main__.py
sap_datasphere_mcp/auth.py
sap_datasphere_mcp/client.py
sap_datasphere_mcp/models.py
sap_datasphere_mcp/production_server.py
sap_datasphere_mcp/server.py
sap_datasphere_mcp-2.0.0.dist-info/METADATA
sap_datasphere_mcp-2.0.0.dist-info/WHEEL
sap_datasphere_mcp-2.0.0.dist-info/entry_points.txt
sap_datasphere_mcp-2.0.0.dist-info/licenses/LICENSE
sap_datasphere_mcp-2.0.0.dist-info/RECORD
